{
  "version": "5",
  "dialect": "mysql",
  "id": "41ca28dc-7263-4cf3-8fda-6de1f342b343",
  "prevId": "00000000-0000-0000-0000-000000000000",
  "tables": {
    "user": {
      "name": "user",
      "columns": {
        "id": {
          "name": "id",
          "type": "serial",
          "primaryKey": false,
          "notNull": true,
          "autoincrement": true
        },
        "name": {
          "name": "name",
          "type": "varchar(50)",
          "primaryKey": false,
          "notNull": true,
          "autoincrement": false
        },
        "email": {
          "name": "email",
          "type": "varchar(100)",
          "primaryKey": false,
          "notNull": true,
          "autoincrement": false
        },
        "password": {
          "name": "password",
          "type": "varchar(65)",
          "primaryKey": false,
          "notNull": true,
          "autoincrement": false
        },
        "reset_token": {
          "name": "reset_token",
          "type": "varchar(100)",
          "primaryKey": false,
          "notNull": false,
          "autoincrement": false
        },
        "created_at": {
          "name": "created_at",
          "type": "timestamp",
          "primaryKey": false,
          "notNull": false,
          "autoincrement": false,
          "default": "(now())"
        },
        "updated_at": {
          "name": "updated_at",
          "type": "timestamp",
          "primaryKey": false,
          "notNull": false,
          "autoincrement": false,
          "default": "(now())"
        }
      },
      "indexes": {},
      "foreignKeys": {},
      "compositePrimaryKeys": {
        "user_id": {
          "name": "user_id",
          "columns": [
            "id"
          ]
        }
      },
      "uniqueConstraints": {
        "user_email_unique": {
          "name": "user_email_unique",
          "columns": [
            "email"
          ]
        }
      }
    }
  },
  "schemas": {},
  "_meta": {
    "schemas": {},
    "tables": {},
    "columns": {}
  }
}